pyurlmapper-0.1.0.dist-info/licenses/LICENSE
urlmapper/__init__.py
urlmapper/core.py
pyurlmapper-0.1.0.dist-info/METADATA
pyurlmapper-0.1.0.dist-info/WHEEL
pyurlmapper-0.1.0.dist-info/top_level.txt
pyurlmapper-0.1.0.dist-info/RECORD
