Metadata-Version: 2.4
Name: pyurlmapper
Version: 0.1.0
Summary: Lightweight URL mapper and proxy with optional DNS helper for local testing
Author: Leonardo
Classifier: Programming Language :: Python :: 3
Classifier: License :: OSI Approved :: MIT License
Requires-Python: >=3.8
License-File: LICENSE
Requires-Dist: flask
Requires-Dist: requests
Requires-Dist: dnslib
Dynamic: author
Dynamic: classifier
Dynamic: description
Dynamic: description-content-type
Dynamic: license-file
Dynamic: requires-dist
Dynamic: requires-python
Dynamic: summary
